{
  "tournament": "Open A-Z Padel Fluvial",
  "slug": "OpenAZPadelFluvial26",
  "section": "Masculinos 4",
  "drawSize": 64,
  "generatedAt": "2026-04-11T21:53:11.057Z",
  "result": [
    {
      "pos": 1,
      "draw": "MAIN",
      "p1": "Rui Vieira",
      "lic1": "17417",
      "pid1": "212192",
      "p2": "Fábio Ferreira",
      "lic2": "26912",
      "pid2": "360518",
      "club": "TheHyveAcademy",
      "pts1": 55.19,
      "lvl1": 6,
      "pts2": 1167.41,
      "lvl2": 5,
      "total": 1222.6000000000001,
      "note": "Seed 1"
    },
    {
      "pos": 2,
      "draw": "MAIN",
      "p1": "Hélder Lopes",
      "lic1": "7287",
      "pid1": "74807",
      "p2": "Filipe Costa",
      "lic2": "",
      "pid2": "",
      "club": "Top-padel Industrial Indoor",
      "pts1": 49.06,
      "lvl1": 6,
      "pts2": 0,
      "lvl2": 6,
      "total": 49.06,
      "note": "Seed 2"
    },
    {
      "pos": 3,
      "draw": "MAIN",
      "p1": "Tiago Loureiro",
      "lic1": "13915",
      "pid1": "174059",
      "p2": "Jaime Ribeiro",
      "lic2": "14767",
      "pid2": "175390",
      "club": "Padel Beat",
      "pts1": 3067.09,
      "lvl1": 4,
      "pts2": 612.5,
      "lvl2": 6,
      "total": 3679.59,
      "note": "Seed 3"
    }
  ]
}